backedarray/__init__.py
backedarray/dense_array.py
backedarray/h5f5_dense_array.py
backedarray/index.py
backedarray/sparse_array.py
backedarray/types.py
backedarray/utils.py
backedarray/zarr_dense_array.py
backedarray-0.0.1.dist-info/METADATA
backedarray-0.0.1.dist-info/WHEEL
backedarray-0.0.1.dist-info/licenses/LICENSE
backedarray-0.0.1.dist-info/RECORD
